{
  "questions": [
    {
      "title": " hggggggggg fdgh fgh\n hgd\nfgh h ",
      "authorId": "42bf39c1-49ff-440e-a170-d5a24e77b832",
      "datetime": 1643551187482,
      "commentNumber": 0,
      "likes": 5,
      "dislikes": 1,
      "id": "0f1a7d94-3eff-4a08-904a-924844532ba3"
    },
    {
      "title": "Naniii",
      "authorId": "4f41bfd8-51f1-4c35-b176-d5a178da510d",
      "datetime": 1643553980035,
      "commentNumber": 1,
      "likes": 10,
      "dislikes": 2,
      "id": "06fd3193-675d-4464-bd30-59dfd36f118a"
    }
  ],
  "comments": [
    {
      "text": "Let's see brah ",
      "authorId": "42bf39c1-49ff-440e-a170-d5a24e77b832",
      "datetime": 1643605577301,
      "postId": "06fd3193-675d-4464-bd30-59dfd36f118a",
      "id": "b5be058f-87b5-46b7-a17d-36cf109e04e8"
    },
    {
      "text": "Let's see brah  asgfdag ",
      "authorId": "42bf39c1-49ff-440e-a170-d5a24e77b832",
      "datetime": 1643605580815,
      "postId": "06fd3193-675d-4464-bd30-59dfd36f118a",
      "id": "220a2f43-c4d7-43bb-a500-0573ec6dfdc3"
    }
  ],
  "users": [
    {
      "firstName": "test",
      "lastName": "testerino",
      "email": "hsemic1991@gmail.com",
      "password": "hehehe",
      "id": "42bf39c1-49ff-440e-a170-d5a24e77b832",
      "numberOfQuestions": 0,
      "numberOfAnswers": 0,
      "dateJoined": 1643580468524
    },
    {
      "firstName": "Haris",
      "lastName": "Semic",
      "email": "test@test.com",
      "password": "testtest",
      "id": "4f41bfd8-51f1-4c35-b176-d5a178da510d",
      "numberOfQuestions": 0,
      "numberOfAnswers": 0,
      "dateJoined": 1643580468524
    }
  ]
}